README
setup.py
django_location_choices/__init__.py
django_location_choices/locations.py
django_location_choices.egg-info/PKG-INFO
django_location_choices.egg-info/SOURCES.txt
django_location_choices.egg-info/dependency_links.txt
django_location_choices.egg-info/not-zip-safe
django_location_choices.egg-info/top_level.txt