Metadata-Version: 1.0
Name: django-location-choices
Version: 1.0
Summary: Django location choices is a simple tuple, prepopulated with countries and states for use in Django models as CHOICES values
Home-page: http://github.com/bmelton/django_location_choices/
Author: Barry Melton
Author-email: barry.melton@gmail.com
License: UNKNOWN
Platform: UNKNOWN
Classifier: Development Status :: 3 - Alpha
Classifier: Framework :: Django
Classifier: Intended Audience :: Developers
Classifier: Operating System :: OS Independent
Classifier: Programming Language :: Python
